README.md
setup.py
juspayp3/Cards.py
juspayp3/Customers.py
juspayp3/JuspayException.py
juspayp3/Orders.py
juspayp3/Payments.py
juspayp3/Wallets.py
juspayp3/__init__.py
juspayp3/config.py
juspayp3/util.py
juspayp3.egg-info/PKG-INFO
juspayp3.egg-info/SOURCES.txt
juspayp3.egg-info/dependency_links.txt
juspayp3.egg-info/requires.txt
juspayp3.egg-info/top_level.txt