Metadata-Version: 1.0
Name: juspayp3
Version: 1.0.0
Summary: Python 3 version of expresscheckout-python-client - JusPay Express Checkout API
Home-page: https://github.com/dhavalsavalia/juspay-expresscheckout-python3-client
Author: Dhaval Savalia
Author-email: dhaval.savalia6@gmail.com
License: MIT
Keywords: juspay expresscheckout payments
Platform: UNKNOWN
